[
  {
    "log_id": 1772845216495,
    "machine_id": 12,
    "operator_id": 14,
    "color": "Green",
    "status": "OK",
    "operator_press_time": "2026-03-07T01:00:16.495Z",
    "cycle_start_time": "2026-03-07T01:00:00.000Z",
    "cycle_end_time": "2026-03-07T03:00:00.000Z",
    "supervisor_id": null,
    "supervisor_badge": null,
    "supervisor_confirmation": null,
    "supervisor_scan_time": null,
    "updated_at": null
  },
  {
    "log_id": 1772852406124,
    "machine_id": 12,
    "operator_id": 14,
    "color": "Yellow",
    "status": "OK",
    "operator_press_time": "2026-03-07T03:00:06.124Z",
    "cycle_start_time": "2026-03-07T03:00:00.000Z",
    "cycle_end_time": "2026-03-07T05:00:00.000Z",
    "supervisor_id": null,
    "supervisor_badge": null,
    "supervisor_confirmation": null,
    "supervisor_scan_time": null,
    "updated_at": null
  },
  {
    "log_id": 1772859857604,
    "machine_id": 12,
    "operator_id": 24,
    "color": "Red",
    "status": "OK",
    "operator_press_time": "2026-03-07T05:04:17.604Z",
    "cycle_start_time": "2026-03-07T05:00:00.000Z",
    "cycle_end_time": "2026-03-07T07:00:00.000Z",
    "supervisor_id": null,
    "supervisor_badge": null,
    "supervisor_confirmation": null,
    "supervisor_scan_time": null,
    "updated_at": null
  },
  {
    "log_id": 1772866849601,
    "machine_id": 12,
    "operator_id": 24,
    "color": "Blue",
    "status": "OK",
    "operator_press_time": "2026-03-07T07:00:49.601Z",
    "cycle_start_time": "2026-03-07T07:00:00.000Z",
    "cycle_end_time": "2026-03-07T09:00:00.000Z",
    "supervisor_id": null,
    "supervisor_badge": null,
    "supervisor_confirmation": null,
    "supervisor_scan_time": null,
    "updated_at": null
  },
  {
    "log_id": 1772874033711,
    "machine_id": 12,
    "operator_id": 24,
    "color": "Green",
    "status": "OK",
    "operator_press_time": "2026-03-07T09:00:33.711Z",
    "cycle_start_time": "2026-03-07T09:00:00.000Z",
    "cycle_end_time": "2026-03-07T11:00:00.000Z",
    "supervisor_id": null,
    "supervisor_badge": null,
    "supervisor_confirmation": null,
    "supervisor_scan_time": null,
    "updated_at": null
  },
  {
    "log_id": 1772881365472,
    "machine_id": 12,
    "operator_id": 24,
    "color": "Yellow",
    "status": "OK",
    "operator_press_time": "2026-03-07T11:02:45.472Z",
    "cycle_start_time": "2026-03-07T11:00:00.000Z",
    "cycle_end_time": "2026-03-07T13:00:00.000Z",
    "supervisor_id": null,
    "supervisor_badge": null,
    "supervisor_confirmation": null,
    "supervisor_scan_time": null,
    "updated_at": null
  }
]